odoo/addons/ssi_voucher_bank_cash/README.rst
odoo/addons/ssi_voucher_bank_cash/__init__.py
odoo/addons/ssi_voucher_bank_cash/__manifest__.py
odoo/addons/ssi_voucher_bank_cash/menu.xml
odoo/addons/ssi_voucher_bank_cash/data/account_voucher_type_data.xml
odoo/addons/ssi_voucher_bank_cash/data/approval_template_bank_payment_data.xml
odoo/addons/ssi_voucher_bank_cash/data/approval_template_bank_receipt_data.xml
odoo/addons/ssi_voucher_bank_cash/data/approval_template_cash_payment_data.xml
odoo/addons/ssi_voucher_bank_cash/data/approval_template_cash_receipt_data.xml
odoo/addons/ssi_voucher_bank_cash/data/ir_sequence_data.xml
odoo/addons/ssi_voucher_bank_cash/data/ir_windows_action_data.xml
odoo/addons/ssi_voucher_bank_cash/data/policy_template_bank_payment_data.xml
odoo/addons/ssi_voucher_bank_cash/data/policy_template_bank_receipt_data.xml
odoo/addons/ssi_voucher_bank_cash/data/policy_template_cash_payment_data.xml
odoo/addons/ssi_voucher_bank_cash/data/policy_template_cash_receipt_data.xml
odoo/addons/ssi_voucher_bank_cash/data/sequence_template_bank_payment_data.xml
odoo/addons/ssi_voucher_bank_cash/data/sequence_template_bank_receipt_data.xml
odoo/addons/ssi_voucher_bank_cash/data/sequence_template_cash_payment_data.xml
odoo/addons/ssi_voucher_bank_cash/data/sequence_template_cash_receipt_data.xml
odoo/addons/ssi_voucher_bank_cash/demo/account_account_demo.xml
odoo/addons/ssi_voucher_bank_cash/demo/account_journal_demo.xml
odoo/addons/ssi_voucher_bank_cash/demo/account_voucher_type_allowed_journal_demo.xml
odoo/addons/ssi_voucher_bank_cash/models/__init__.py
odoo/addons/ssi_voucher_bank_cash/models/bank_payment.py
odoo/addons/ssi_voucher_bank_cash/models/bank_receipt.py
odoo/addons/ssi_voucher_bank_cash/models/cash_payment.py
odoo/addons/ssi_voucher_bank_cash/models/cash_receipt.py
odoo/addons/ssi_voucher_bank_cash/models/mixin_bank_voucher.py
odoo/addons/ssi_voucher_bank_cash/security/ir.model.access.csv
odoo14_addon_ssi_voucher_bank_cash-14.0.4.0.0.dist-info/METADATA
odoo14_addon_ssi_voucher_bank_cash-14.0.4.0.0.dist-info/WHEEL
odoo14_addon_ssi_voucher_bank_cash-14.0.4.0.0.dist-info/top_level.txt
odoo14_addon_ssi_voucher_bank_cash-14.0.4.0.0.dist-info/RECORD
